setup.py
clirender/__init__.py
clirender.egg-info/PKG-INFO
clirender.egg-info/SOURCES.txt
clirender.egg-info/dependency_links.txt
clirender.egg-info/requires.txt
clirender.egg-info/top_level.txt
clirender/layout/__init__.py
clirender/layout/api.py
clirender/layout/exceptions.py
clirender/layout/layout.py
clirender/layout/patch.py
clirender/layout/safe_eval.py
clirender/layout/xml_parser.py
clirender/layout/libs/__init__.py
clirender/layout/libs/all.py
clirender/layout/libs/conditional.py
clirender/layout/libs/events.py
clirender/layout/libs/keypress.py
clirender/layout/libs/library.py
clirender/layout/libs/loops.py
clirender/layout/libs/query.py
clirender/layout/libs/render.py
clirender/layout/libs/scrollable.py
clirender/layout/libs/tabswitch.py
clirender/layout/nodes/__init__.py
clirender/layout/nodes/alignright.py
clirender/layout/nodes/container.py
clirender/layout/nodes/element.py
clirender/layout/nodes/fromxml.py
clirender/layout/nodes/generator.py
clirender/layout/nodes/node.py
clirender/layout/nodes/rect.py
clirender/layout/nodes/stackpanel.py
clirender/layout/nodes/switch.py
clirender/layout/nodes/text.py
clirender/screen/__init__.py
clirender/screen/screen.py
clirender/screen/size.py