Metadata-Version: 1.0
Name: clirender
Version: 0.48
Summary: CLI rendering engine for Python
Home-page: https://github.com/imachug/clirender
Author: Ivanq
Author-email: imachug@gmail.com
License: UNKNOWN
Keywords: cli,cli-application,rendering-2d-graphics
Platform: UNKNOWN
